sanitize_filename/__init__.py
sanitize_filename/sanitize_filename.py
sanitize_filename-1.2.0.dist-info/LICENSE
sanitize_filename-1.2.0.dist-info/METADATA
sanitize_filename-1.2.0.dist-info/WHEEL
sanitize_filename-1.2.0.dist-info/top_level.txt
sanitize_filename-1.2.0.dist-info/RECORD
