Metadata-Version: 2.1
Name: sanitize-filename
Version: 1.2.0
Summary: A permissive filename sanitizer.
Home-page: https://gitlab.com/jplusplus/sanitize-filename
Author: Leo Wallentin | J++ Stockholm
Author-email: mejl@leowallentin.se
License: UNKNOWN
Platform: UNKNOWN
Classifier: Programming Language :: Python :: 3
Classifier: License :: OSI Approved :: MIT License
Classifier: Operating System :: OS Independent
Requires-Python: ~=3.7
